Datapath_and_controlpath/controlpath.v
module controller(LdA,LdB,LdP,decB,clrP,done,clk,eqz,start);
    input clk,eqz,start;
    output reg LdA,LdB,LdP,decB,clrP,done;

    reg [2:0] state;
    parameter S0 = 3'b000, S1 = 3'b001, S2 = 3'b010, S3 = 3'b011, S4 = 3'b100;

    always @(posedge clk)
        begin
            case (state)
                S0: if(start) state<= S1;
                S1: state <= S2;
                S2: state <= S3;
                S3: #2 if (eqz) state <= S4;
                S4: state <= S4;
                default : state <= S0;
            endcase
        end
    
    always @(state)begin
        case (state)
            S0: begin #1 LdA=0;LdB=0;LdP=0;decB=0;clrP=0; end
            S1: begin #1 LdA=1; end
            S2: begin #1 LdA=0;LdB=1;clrP=1; end
            S3: begin #1 LdB=0;clrP=0;LdP=1;decB=1; end
            S4: begin #1 LdP=0;decB=0;done=1; end
        endcase
    end
endmodule

Datapath_and_controlpath/module.v
module PIPO1(d_out,d_in,LdA,clk);
    input [15:0] d_in;
    input LdA,clk;
    output reg [15:0] d_out;

    always @(posedge clk)
        if (LdA) d_out <= d_in;
endmodule

module PIPO2(d_out,d_in,LdP,clrP,clk);
    input [15:0] d_in;
    input LdP,clrP,clk;
    output reg [15:0] d_out;

    always @(posedge clk)
        if(clrP)    d_out <= 16'b0;
        else if (LdP) d_out <= d_in;
endmodule

module CNTR(d_out,d_in,LdB,decB,clk);
    input [15:0] d_in;
    input LdB,decB,clk;
    output reg [15:0] d_out;
    always @(posedge clk)
        if(decB) d_out <= d_out -1;
        else if(LdB) d_out <= d_in;
endmodule

module ADDR(d_out,in1,in2);
    input [15:0] in1,in2;
    output reg [15:0] d_out;
    always @(*)
        d_out <= in1 + in2;
endmodule

module COMP(eqz,d_in);
    input [15:0] d_in;
    output eqz;
    assign eqz = (d_in == 0);
endmodule

Datapath_and_controlpath/datapath.v
module datapath (eqz,LdA,LdB,LdP,clrP,decB,data_in,clk);
    input LdA,LdB,LdP,clrP,decB,clk;
    input [15:0] data_in;
    output eqz;
    wire [15:0] X,Y,Z,Bout,Bus;

    assign Bus = data_in;

    PIPO1 A(X,Bus,LdA,clk);
    PIPO2 P(Y,Z,LdP,clrP,clk);
    CNTR B(Bout,Bus,LdB,decB,clk);
    ADDR ADD(Z,X,Y);
    COMP E(eqz,Bout);
endmodule

Datapath_and_controlpath/testbench.v
module testbench;
    reg[15:0] data_in;
    reg clk, start;
    wire done;

    datapath DP(eqz,LdA,LdB,LdP,clrP,decB,data_in,clk);
    controller CP(LdA,LdB,LdP,decB,clrP,done,clk,eqz,start);

    initial begin
        clk = 1'b0;
        #3 start = 1'b1;
        #500 $finish;
    end

    always #5 clk = ~clk;

    initial begin
        #17 data_in = 17;
        #10 data_in = 5;
    end

    initial begin
        $monitor($time,"%d %b",DP.Y,done);
        $dumpfile("mult.vcd");
        $dumpvars(0,testbench);
    end
endmodule

Datapath_and_controlpath/mult.vcd
$date
	Fri May 22 14:05:40 2026
$end
$version
	Icarus Verilog
$end
$timescale
	1s
$end
$scope module testbench $end
$var wire 1 ! eqz $end
$var wire 1 " done $end
$var wire 1 # decB $end
$var wire 1 $ clrP $end
$var wire 1 % LdP $end
$var wire 1 & LdB $end
$var wire 1 ' LdA $end
$var reg 1 ( clk $end
$var reg 16 ) data_in [15:0] $end
$var reg 1 * start $end
$scope module CP $end
$var wire 1 ( clk $end
$var wire 1 * start $end
$var wire 1 ! eqz $end
$var reg 1 ' LdA $end
$var reg 1 & LdB $end
$var reg 1 % LdP $end
$var reg 1 $ clrP $end
$var reg 1 # decB $end
$var reg 1 " done $end
$var reg 3 + state [2:0] $end
$upscope $end
$scope module DP $end
$var wire 16 , Bus [15:0] $end
$var wire 1 ' LdA $end
$var wire 1 & LdB $end
$var wire 1 % LdP $end
$var wire 1 ( clk $end
$var wire 1 $ clrP $end
$var wire 16 - data_in [15:0] $end
$var wire 1 # decB $end
$var wire 1 ! eqz $end
$var wire 16 . Z [15:0] $end
$var wire 16 / Y [15:0] $end
$var wire 16 0 X [15:0] $end
$var wire 16 1 Bout [15:0] $end
$scope module A $end
$var wire 1 ' LdA $end
$var wire 1 ( clk $end
$var wire 16 2 d_in [15:0] $end
$var reg 16 3 d_out [15:0] $end
$upscope $end
$scope module ADD $end
$var wire 16 4 in1 [15:0] $end
$var wire 16 5 in2 [15:0] $end
$var reg 16 6 d_out [15:0] $end
$upscope $end
$scope module B $end
$var wire 1 & LdB $end
$var wire 1 ( clk $end
$var wire 16 7 d_in [15:0] $end
$var wire 1 # decB $end
$var reg 16 8 d_out [15:0] $end
$upscope $end
$scope module E $end
$var wire 16 9 d_in [15:0] $end
$var wire 1 ! eqz $end
$upscope $end
$scope module P $end
$var wire 1 % LdP $end
$var wire 1 ( clk $end
$var wire 1 $ clrP $end
$var wire 16 : d_in [15:0] $end
$var reg 16 ; d_out [15:0] $end
$upscope $end
$upscope $end
$upscope $end
$enddefinitions $end
#0
$dumpvars
bx ;
bx :
bx 9
bx 8
bx 7
bx 6
bx 5
bx 4
bx 3
bx 2
bx 1
bx 0
bx /
bx .
bx -
bx ,
bx +
x*
bx )
0(
x'
x&
x%
x$
x#
x"
x!
$end
#3
1*
#5
b0 +
1(
#6
0$
0#
0%
0&
0'
#10
0(
#15
b1 +
1(
#16
1'
#17
b10001 ,
b10001 2
b10001 7
b10001 )
b10001 -
#20
0(
#25
b10001 0
b10001 3
b10001 4
b10 +
1(
#26
1$
1&
0'
#27
b101 ,
b101 2
b101 7
b101 )
b101 -
#30
0(
#35
b10001 .
b10001 6
b10001 :
b11 +
0!
b101 1
b101 8
b101 9
b0 /
b0 5
b0 ;
1(
#36
1#
1%
0$
0&
#40
0(
#45
b100010 .
b100010 6
b100010 :
b10001 /
b10001 5
b10001 ;
b100 1
b100 8
b100 9
1(
#50
0(
#55
b110011 .
b110011 6
b110011 :
b11 1
b11 8
b11 9
b100010 /
b100010 5
b100010 ;
1(
#60
0(
#65
b1000100 .
b1000100 6
b1000100 :
b110011 /
b110011 5
b110011 ;
b10 1
b10 8
b10 9
1(
#70
0(
#75
b1010101 .
b1010101 6
b1010101 :
b1 1
b1 8
b1 9
b1000100 /
b1000100 5
b1000100 ;
1(
#80
0(
#85
b1100110 .
b1100110 6
b1100110 :
b1010101 /
b1010101 5
b1010101 ;
1!
b0 1
b0 8
b0 9
1(
#87
b100 +
#88
1"
0#
0%
