FIFO/memblock.v
module FIFOMemBlock(clk,writeN,readN,emptyN,wr_addr,rd_addr,data_in,data_out);
input clk, writeN,readN,emptyN;
input [`FCWIDTH-1:0] wr_addr,rd_addr;
input [`FWIDTH-1:0] data_in;
output [`FWIDTH-1:0] data_out;

reg [`FWIDTH-1:0] FIFO[`FDEPTH-1:0];

assign data_out =  (!readN && emptyN) ? FIFO[rd_addr] : 32'bx;
always @(posedge clk)
begin
    if(writeN == 1'b0)
        FIFO[wr_addr] <= data_in;
end
endmodule

FIFO/fifo.v
`define FWIDTH 32 
`define FDEPTH 4
`define FCWIDTH 2
module FIFO(clk,RstN,Data_in,InN,clrN,OutN,F_data,F_FullN,F_EmptyN,F_LastN,F_SLastN,F_firstN);
input clk,RstN,InN,clrN,OutN;
input [`FWIDTH-1:0] Data_in;
output [`FWIDTH-1:0] F_data;
output reg F_FullN,F_EmptyN,F_LastN,F_SLastN,F_firstN;

reg [`FCWIDTH-1:0] fcounter;
reg [`FCWIDTH-1:0] rdptr;
reg [`FCWIDTH-1:0] wrptr;
wire [`FWIDTH-1:0] FIFODataOut;
wire [`FWIDTH-1:0] FIFODataIn;

wire readN = OutN;
wire writeN = InN;

assign F_data = FIFODataOut;
assign FIFODataIn = Data_in;

FIFOMemBlock FIFO1(clk,writeN,readN,F_EmptyN,wrptr,rdptr,FIFODataIn,FIFODataOut);

always @(posedge clk or negedge RstN)
begin
    if(!RstN)begin
        fcounter <= 0;
        rdptr <= 0;
        wrptr <= 0;
    end
    else begin
        if(!clrN) begin
            fcounter <= 0;
            rdptr <= 0;
            wrptr <= 0;
        end
    
    else begin
        if(!writeN)
            wrptr <= wrptr + 1;
        if(!readN)
            rdptr <= rdptr + 1;
        if(!writeN && readN && F_FullN)
            fcounter <= fcounter + 1;
        else if (writeN && !readN && F_EmptyN)
            fcounter <= fcounter + 1; 
    end
end
end

always @(posedge clk or negedge RstN)
begin
    if(!RstN)
        F_EmptyN <= 1'b0;
    else begin
        if(clrN == 1'b1) begin
            if(F_EmptyN == 1'b0 && writeN == 1'b0)
                F_EmptyN <= 1'b1;
            else if (F_firstN == 1'b0 && readN == 1'b0 && writeN == 1'b1)
                F_EmptyN <= 1'b0;  
        end
        else 
            F_EmptyN <= 1'b0;
    end 
end

always @(posedge clk or negedge RstN)
begin
    if(!RstN)
        F_firstN <= 1'b1;
    else begin
        if(clrN == 1'b1) begin
            if((F_EmptyN == 1'b0 && writeN == 1'b0) || (fcounter == 2 && readN == 1'b0 && writeN == 1'b1))
                F_firstN <= 1'b0;

            else if (F_firstN == 1'b0 && (readN ^ writeN))
                F_firstN <= 1'b1;     
        end
        else begin
            F_firstN <= 1'b1;
        end
    end 
end

always @(posedge clk or negedge RstN)
begin
    if(!RstN)
        F_SLastN <= 1'b1;
    else begin
        if(clrN == 1'b1) begin
            if((F_LastN==1'b0 && readN==1'b0 && writeN==1'b1) || (fcounter == (`FDEPTH-3) && writeN == 1'b0 && readN == 1'b1))
                F_SLastN <= 1'b0;
            else if(F_SLastN == 1'b0 && (readN ^ writeN))
                F_SLastN <= 1'b1;
        end
        else 
            F_SLastN <= 1'b1;
    end 
end

always @(posedge clk or negedge RstN)
begin
    if(!RstN)
        F_LastN <= 1'b1;
        else begin
            if(clrN==1'b1)begin
                if((F_FullN==1'b0 && readN == 1'b0) || (fcounter == (`FDEPTH-2) && writeN==1'b0 && readN==1'b1))
                    F_LastN <= 1'b0;
                else if(F_LastN == 1'b0 && (readN ^ writeN))
                    F_LastN <= 1'b1;
            end
            else F_LastN <= 1'b1;
        end 
end

always @(posedge clk or negedge RstN)
begin
    if(!RstN)
        F_FullN <= 1'b1;
    else begin
        if(clrN == 1'b1) begin
            if(F_LastN == 1'b0 && writeN==1'b0 && readN==1'b1)
                F_FullN <= 1'b0;
            else if (F_FullN == 1'b0 && readN == 1'b0)
                F_FullN <= 1'b1;     
        end
        else F_FullN <= 1'b1;
    end
end
endmodule

FIFO/testbench.v
`timescale 1ns/1ps

`define FWIDTH 32
`define FDEPTH 4
`define FCWIDTH 2

module FIFO_tb;

    reg clk;
    reg RstN;
    reg InN;
    reg clrN;
    reg OutN;
    reg [`FWIDTH-1:0] Data_in;

    wire [`FWIDTH-1:0] F_data;
    wire F_FullN;
    wire F_EmptyN;
    wire F_LastN;
    wire F_SLastN;
    wire F_firstN;

    FIFO dut (
        .clk(clk),
        .RstN(RstN),
        .Data_in(Data_in),
        .InN(InN),
        .clrN(clrN),
        .OutN(OutN),
        .F_data(F_data),
        .F_FullN(F_FullN),
        .F_EmptyN(F_EmptyN),
        .F_LastN(F_LastN),
        .F_SLastN(F_SLastN),
        .F_firstN(F_firstN)
    );

    always #5 clk = ~clk;

    initial begin
        $dumpfile("fifo_tb.vcd");
        $dumpvars(0, FIFO_tb);

        clk = 0;
        RstN = 0;
        clrN = 1;
        InN = 1;
        OutN = 1;
        Data_in = 0;

        #20;
        RstN = 1;

        // Write first data
        #10;
        Data_in = 32'hAAAA_0001;
        InN = 0;
        OutN = 1;

        #10;
        InN = 1;

        // Write second data
        #10;
        Data_in = 32'hBBBB_0002;
        InN = 0;

        #10;
        InN = 1;

        // Write third data
        #10;
        Data_in = 32'hCCCC_0003;
        InN = 0;

        #10;
        InN = 1;

        // Write fourth data
        #10;
        Data_in = 32'hDDDD_0004;
        InN = 0;

        #10;
        InN = 1;

        // Read first data
        #10;
        OutN = 0;
        InN = 1;

        #10;
        OutN = 1;

        // Read second data
        #10;
        OutN = 0;

        #10;
        OutN = 1;

        // Simultaneous read and write
        #10;
        Data_in = 32'hEEEE_0005;
        InN = 0;
        OutN = 0;

        #10;
        InN = 1;
        OutN = 1;

        // Clear FIFO
        #10;
        clrN = 0;

        #10;
        clrN = 1;

        // Write after clear
        #10;
        Data_in = 32'h1234_5678;
        InN = 0;
        OutN = 1;

        #10;
        InN = 1;

        // Read after clear
        #10;
        OutN = 0;

        #10;
        OutN = 1;

        #50;
        $finish;
    end

    initial begin
        $monitor("Time=%0t RstN=%b clrN=%b InN=%b OutN=%b Data_in=%h F_data=%h FullN=%b EmptyN=%b LastN=%b SLastN=%b FirstN=%b",
                 $time, RstN, clrN, InN, OutN, Data_in, F_data,
                 F_FullN, F_EmptyN, F_LastN, F_SLastN, F_firstN);
    end

endmodule

FIFO/fifo_tb.vcd
$date
	Sat May 30 09:46:59 2026
$end
$version
	Icarus Verilog
$end
$timescale
	1ps
$end
$scope module FIFO_tb $end
$var wire 1 ! F_firstN $end
$var wire 32 " F_data [31:0] $end
$var wire 1 # F_SLastN $end
$var wire 1 $ F_LastN $end
$var wire 1 % F_FullN $end
$var wire 1 & F_EmptyN $end
$var reg 32 ' Data_in [31:0] $end
$var reg 1 ( InN $end
$var reg 1 ) OutN $end
$var reg 1 * RstN $end
$var reg 1 + clk $end
$var reg 1 , clrN $end
$scope module dut $end
$var wire 32 - Data_in [31:0] $end
$var wire 32 . FIFODataIn [31:0] $end
$var wire 32 / F_data [31:0] $end
$var wire 1 ( InN $end
$var wire 1 ) OutN $end
$var wire 1 * RstN $end
$var wire 1 + clk $end
$var wire 1 , clrN $end
$var wire 1 0 readN $end
$var wire 1 1 writeN $end
$var wire 32 2 FIFODataOut [31:0] $end
$var reg 1 & F_EmptyN $end
$var reg 1 % F_FullN $end
$var reg 1 $ F_LastN $end
$var reg 1 # F_SLastN $end
$var reg 1 ! F_firstN $end
$var reg 2 3 fcounter [1:0] $end
$var reg 2 4 rdptr [1:0] $end
$var reg 2 5 wrptr [1:0] $end
$scope module FIFO1 $end
$var wire 1 + clk $end
$var wire 32 6 data_in [31:0] $end
$var wire 1 & emptyN $end
$var wire 2 7 rd_addr [1:0] $end
$var wire 1 0 readN $end
$var wire 2 8 wr_addr [1:0] $end
$var wire 1 1 writeN $end
$var wire 32 9 data_out [31:0] $end
$upscope $end
$upscope $end
$upscope $end
$enddefinitions $end
#0
$dumpvars
bx 9
b0 8
b0 7
b0 6
b0 5
b0 4
b0 3
bx 2
11
10
bx /
b0 .
b0 -
1,
0+
0*
1)
1(
b0 '
0&
1%
1$
1#
bx "
1!
$end
#5000
1+
#10000
0+
#15000
1+
#20000
0+
1*
#25000
1+
#30000
0+
01
0(
b10101010101010100000000000000001 .
b10101010101010100000000000000001 6
b10101010101010100000000000000001 '
b10101010101010100000000000000001 -
#35000
b1 3
b1 5
b1 8
1&
0!
1+
#40000
0+
11
1(
#45000
1+
#50000
0+
01
0(
b10111011101110110000000000000010 .
b10111011101110110000000000000010 6
b10111011101110110000000000000010 '
b10111011101110110000000000000010 -
#55000
b10 3
b10 5
b10 8
1!
0#
1+
#60000
0+
11
1(
#65000
1+
#70000
0+
01
0(
b11001100110011000000000000000011 .
b11001100110011000000000000000011 6
b11001100110011000000000000000011 '
b11001100110011000000000000000011 -
#75000
b11 3
b11 5
b11 8
1#
0$
1+
#80000
0+
11
1(
#85000
1+
#90000
0+
01
0(
b11011101110111010000000000000100 .
b11011101110111010000000000000100 6
b11011101110111010000000000000100 '
b11011101110111010000000000000100 -
#95000
b0 3
b0 5
b0 8
1$
0%
1+
#100000
0+
11
1(
#105000
1+
#110000
b10101010101010100000000000000001 "
b10101010101010100000000000000001 /
b10101010101010100000000000000001 2
b10101010101010100000000000000001 9
0+
00
0)
#115000
b10111011101110110000000000000010 "
b10111011101110110000000000000010 /
b10111011101110110000000000000010 2
b10111011101110110000000000000010 9
b1 3
b1 4
b1 7
0$
1%
1+
#120000
bx "
bx /
bx 2
bx 9
0+
10
1)
#125000
1+
#130000
b10111011101110110000000000000010 "
b10111011101110110000000000000010 /
b10111011101110110000000000000010 2
b10111011101110110000000000000010 9
0+
00
0)
#135000
b11001100110011000000000000000011 "
b11001100110011000000000000000011 /
b11001100110011000000000000000011 2
b11001100110011000000000000000011 9
b10 3
b10 4
b10 7
0#
1$
1+
#140000
bx "
bx /
bx 2
bx 9
0+
10
1)
#145000
1+
#150000
b11001100110011000000000000000011 "
b11001100110011000000000000000011 /
b11001100110011000000000000000011 2
b11001100110011000000000000000011 9
0+
00
0)
01
0(
b11101110111011100000000000000101 .
b11101110111011100000000000000101 6
b11101110111011100000000000000101 '
b11101110111011100000000000000101 -
#155000
b11011101110111010000000000000100 "
b11011101110111010000000000000100 /
b11011101110111010000000000000100 2
b11011101110111010000000000000100 9
b11 4
b11 7
b1 5
b1 8
1+
#160000
bx "
bx /
bx 2
bx 9
0+
10
1)
11
1(
#165000
1+
#170000
0+
0,
#175000
b0 5
b0 8
b0 4
b0 7
b0 3
0&
1#
1+
#180000
0+
1,
#185000
1+
#190000
0+
01
0(
b10010001101000101011001111000 .
b10010001101000101011001111000 6
b10010001101000101011001111000 '
b10010001101000101011001111000 -
#195000
b1 3
b1 5
b1 8
1&
0!
1+
#200000
0+
11
1(
#205000
1+
#210000
b10010001101000101011001111000 "
b10010001101000101011001111000 /
b10010001101000101011001111000 2
b10010001101000101011001111000 9
0+
00
0)
#215000
bx "
bx /
bx 2
bx 9
b10 3
b1 4
b1 7
0&
1!
1+
#220000
0+
10
1)
